AH_Music_player/Music_player.py
AH_Music_player/__init__.py
ah_music_player-0.0.1.dist-info/licenses/LICENSE
ah_music_player-0.0.1.dist-info/METADATA
ah_music_player-0.0.1.dist-info/WHEEL
ah_music_player-0.0.1.dist-info/top_level.txt
ah_music_player-0.0.1.dist-info/RECORD
