Metadata-Version: 2.4
Name: AH_music_player
Version: 0.0.1
Summary: A package to make a music player in python written using pygame and pillow and tkinter
Author-email: Ahoora Rashidi Khani Abadi <ahoorarashidi47@gmail.com>
License: Copyright (c) 2025 Ahoora Rashidi Khani Abadi
Project-URL: Homepage, https://github.com/pypa/sampleproject
Project-URL: Bug Tracker, https://github.com/pypa/sampleproject/issues
Classifier: Programming Language :: Python :: 3
Classifier: License :: OSI Approved :: MIT License
Classifier: Operating System :: OS Independent
Requires-Python: >=3.7
License-File: LICENSE
Dynamic: license-file
